torchspatial/.DS_Store
torchspatial/SpatialRelationEncoder.py
torchspatial/__init__.py
torchspatial/analysis.py
torchspatial/baselines.py
torchspatial/data_utils.py
torchspatial/dataloader.py
torchspatial/datasets.py
torchspatial/eval_analysis.py
torchspatial/eval_helper.py
torchspatial/example.sh
torchspatial/grid_predictor.py
torchspatial/losses.py
torchspatial/models.py
torchspatial/module.py
torchspatial/ocean_mask.npy
torchspatial/paths.py
torchspatial/process_result.py
torchspatial/readsynthetic.py
torchspatial/run_dfs.sh
torchspatial/run_evaluation.py
torchspatial/run_spherec.sh
torchspatial/spatial_self_information.py
torchspatial/surprisal.py
torchspatial/train_tang_baseline.py
torchspatial/train_unsuper.py
torchspatial/trainer.py
torchspatial/trainer_helper.py
torchspatial/utils.py
torchspatial-0.0.3.dist-info/LICENSE
torchspatial-0.0.3.dist-info/METADATA
torchspatial-0.0.3.dist-info/WHEEL
torchspatial-0.0.3.dist-info/RECORD
