Metadata-Version: 2.1
Name: TorchSpatial
Version: 0.0.3
Summary: TorchSpatial offers a comprehensive framework and benchmark suite designed to advance spatial representation learning (SRL)
License: MIT
Author: SEAI Lab
Author-email: gengchen.mai@austin.utexas.edu
Requires-Python: >=3.8,<4.0
Classifier: License :: OSI Approved :: MIT License
Classifier: Programming Language :: Python :: 3
Classifier: Programming Language :: Python :: 3.8
Classifier: Programming Language :: Python :: 3.9
Classifier: Programming Language :: Python :: 3.10
Classifier: Programming Language :: Python :: 3.11
Classifier: Programming Language :: Python :: 3.12
Requires-Dist: matplotlib (>=3.3.0,<4.0.0)
Requires-Dist: numpy (>=1.21.0,<1.27.0)
Requires-Dist: scikit-learn (>=0.24.0,<2.0.0)
Requires-Dist: scipy (>=1.5.0,<2.0.0)
Requires-Dist: torch (>=1.9.0,<2.4.0)
Requires-Dist: torchaudio (>=2.3.0,<2.5.0)
